myjwt/Exception.py
myjwt/__init__.py
myjwt/modify_jwt.py
myjwt/myjwt_cli.py
myjwt/user_interface.py
myjwt/utils.py
myjwt/variables.py
myjwt/vulnerabilities.py
tests/__init__.py
tests/test_modify_jwt.py
tests/test_myjwt_cli.py
tests/test_utils.py
tests/test_vulnerabilities.py
myjwt-2.0.0.dist-info/LICENSE
myjwt-2.0.0.dist-info/METADATA
myjwt-2.0.0.dist-info/WHEEL
myjwt-2.0.0.dist-info/entry_points.txt
myjwt-2.0.0.dist-info/top_level.txt
myjwt-2.0.0.dist-info/RECORD
