Metadata-Version: 2.1
Name: myjwt
Version: 2.0.0
Summary: Pentesting Tool for JWT(JSON Web Tokens).Modify/Crack/Check Your jwt.
Home-page: https://github.com/mBouamama/MyJWT
Author: mBouamama
Author-email: matthieubouamama@gmail.com
Classifier: Development Status :: 5 - Production/Stable
Classifier: Environment :: Console
Classifier: Intended Audience :: Developers
Classifier: License :: OSI Approved :: MIT License
Classifier: Operating System :: OS Independent
Classifier: Programming Language :: Python :: 3
Classifier: Programming Language :: Python
Classifier: Programming Language :: Python :: 3 :: Only
Classifier: Programming Language :: Python :: 3.10
Classifier: Programming Language :: Python :: 3.11
Classifier: Programming Language :: Python :: 3.12
Classifier: Topic :: Security
Classifier: Topic :: Internet :: WWW/HTTP
Requires-Python: >=3.10
License-File: LICENSE
